contextmemory/__init__.py
contextmemory/py.typed
contextmemory/core/__init__.py
contextmemory/core/openai_client.py
contextmemory/core/settings.py
contextmemory/db/__init__.py
contextmemory/db/database.py
contextmemory/db/models/__init__.py
contextmemory/db/models/conversation.py
contextmemory/db/models/conversation_summary.py
contextmemory/db/models/memory.py
contextmemory/db/models/message.py
contextmemory/memory/__init__.py
contextmemory/memory/bubble_creator.py
contextmemory/memory/connection_finder.py
contextmemory/memory/embeddings.py
contextmemory/memory/extractor.py
contextmemory/memory/memory.py
contextmemory/memory/similar_memory_search.py
contextmemory/memory/similarity.py
contextmemory/memory/tool_classifier.py
contextmemory/memory/vector_store.py
contextmemory/memory/add/add_extraction_phase.py
contextmemory/memory/add/add_updation_phase.py
contextmemory/summary/summary_generator.py
contextmemory/utils/extraction_system_prompt.py
contextmemory/utils/summary_generator_prompt.py
contextmemory/utils/tool_call_system_prompt.py
contextmemory-0.2.0.dist-info/licenses/LICENSE
contextmemory-0.2.0.dist-info/METADATA
contextmemory-0.2.0.dist-info/WHEEL
contextmemory-0.2.0.dist-info/top_level.txt
contextmemory-0.2.0.dist-info/RECORD
