Metadata-Version: 2.4
Name: contextmemory
Version: 0.2.0
Summary: Long-term memory system for AI conversations
Author-email: Samiksha Shukla <samikshasy2908@gmail.com>
License: MIT
Project-URL: Homepage, https://github.com/samiksha0shukla/context-memory
Project-URL: Repository, https://github.com/samiksha0shukla/context-memory
Project-URL: Issues, https://github.com/samiksha0shukla/context-memory/issues
Keywords: ai,memory,llm,openai,context,conversation,long-term-memory,mem0,supermemory
Classifier: Development Status :: 4 - Beta
Classifier: Intended Audience :: Developers
Classifier: License :: OSI Approved :: MIT License
Classifier: Operating System :: OS Independent
Classifier: Programming Language :: Python :: 3
Classifier: Programming Language :: Python :: 3.10
Classifier: Programming Language :: Python :: 3.11
Classifier: Programming Language :: Python :: 3.12
Classifier: Topic :: Scientific/Engineering :: Artificial Intelligence
Requires-Python: >=3.10
License-File: LICENSE
Requires-Dist: openai>=2.0.0
Requires-Dist: sqlalchemy>=2.0.0
Requires-Dist: pydantic>=2.0.0
Requires-Dist: psycopg2-binary>=2.9.0
Requires-Dist: python-dotenv>=1.0.0
Requires-Dist: faiss-cpu>=1.7.0
Requires-Dist: numpy>=1.24.0
Provides-Extra: dev
Requires-Dist: pytest>=7.0.0; extra == "dev"
Requires-Dist: black>=23.0.0; extra == "dev"
Requires-Dist: ruff>=0.1.0; extra == "dev"
Dynamic: license-file
